pyorientdb/__init__.py
pyorientdb/constants.py
pyorientdb/exceptions.py
pyorientdb/groovy.py
pyorientdb/hexdump.py
pyorientdb/messages/__init__.py
pyorientdb/messages/cluster.py
pyorientdb/messages/commands.py
pyorientdb/messages/connection.py
pyorientdb/messages/database.py
pyorientdb/messages/records.py
pyorientdb/ogm/__init__.py
pyorientdb/ogm/batch.py
pyorientdb/ogm/broker.py
pyorientdb/ogm/commands.py
pyorientdb/ogm/config.py
pyorientdb/ogm/declarative.py
pyorientdb/ogm/edge.py
pyorientdb/ogm/element.py
pyorientdb/ogm/exceptions.py
pyorientdb/ogm/graph.py
pyorientdb/ogm/operators.py
pyorientdb/ogm/property.py
pyorientdb/ogm/query.py
pyorientdb/ogm/query_utils.py
pyorientdb/ogm/vertex.py
pyorientdb/ogm/what.py
pyorientdb/orient.py
pyorientdb/otypes.py
pyorientdb/scripts.py
pyorientdb/serializations.py
pyorientdb/utils.py
pyorientdb-1.0.0.dist-info/LICENSE
pyorientdb-1.0.0.dist-info/WHEEL
pyorientdb-1.0.0.dist-info/METADATA
pyorientdb-1.0.0.dist-info/RECORD
