Metadata-Version: 2.1
Name: pyorientdb
Version: 1.0.0
Summary: OrientDB native client library
Home-page: https://github.com/brucetony/pyorientdb
License: Apache-2.0
Author: Bruce Schultz
Author-email: bschultz013@gmail.com
Maintainer: Bruce Schultz
Maintainer-email: bschultz013@gmail.com
Classifier: Development Status :: 5 - Production/Stable
Classifier: Environment :: Console
Classifier: License :: OSI Approved :: Apache Software License
Classifier: Operating System :: OS Independent
Classifier: Programming Language :: Python
Classifier: Programming Language :: Python :: 2
Classifier: Programming Language :: Python :: 2.7
Classifier: Programming Language :: Python :: 3
Classifier: Programming Language :: Python :: 3 :: Only
Classifier: Programming Language :: Python :: 3.10
Classifier: Programming Language :: Python :: 3.4
Classifier: Programming Language :: Python :: 3.5
Classifier: Programming Language :: Python :: 3.6
Classifier: Programming Language :: Python :: 3.7
Classifier: Programming Language :: Python :: 3.8
Classifier: Programming Language :: Python :: 3.9
Project-URL: Issue Tracker, https://github.com/brucetony/pyorientdb/issues
Project-URL: Source Code, https://github.com/brucetony/pyorientdb
